{
  "timestamp": "2026-03-12T03:06:30.970230Z",
  "python": "3.11.8",
  "platform": "macOS-26.2-arm64-arm-64bit",
  "git_commit": "2c3e94e8e5376a82f67851df18f9f7e498590aba",
  "config_hash": "539f7436f1f767e9867f3fbb269a8d22e6f9f9b5e891ca00982b3e2aa821c3ac",
  "config": {
    "varsets": [
      "parsimonious",
      "bop"
    ],
    "models": [
      "MS-VAR",
      "XGBoost"
    ],
    "horizon": 1,
    "split": "test",
    "n_aligned_obs": 27,
    "bootstrap_reps": 10,
    "block_length": 3,
    "ci_level": 0.95,
    "random_seed": 42,
    "headline_model": "MS-VAR",
    "benchmark_model": "Naive",
    "headline_varsets": [
      "parsimonious",
      "bop"
    ],
    "aligned_window_start": "2023-01-01",
    "aligned_window_end": "2025-03-01",
    "headline_reductions": [
      {
        "headline_model": "MS-VAR",
        "benchmark_model": "Naive",
        "n_obs": 36,
        "rmse_model": 311.7527123873274,
        "rmse_benchmark": 1178.9472483420434,
        "rmse_gain": 867.194535954716,
        "rmse_ratio": 0.2644331311903447,
        "pct_reduction": 73.55668688096553,
        "n_bootstrap": 10,
        "block_length": 4,
        "ci_level": 0.95,
        "bootstrap_method": "stationary_block",
        "rmse_model_ci_lower": 263.95018138697895,
        "rmse_model_ci_upper": 352.5853001708197,
        "rmse_model_boot_std": 32.456560610082356,
        "rmse_benchmark_ci_lower": 938.006719650304,
        "rmse_benchmark_ci_upper": 1435.1980218283418,
        "rmse_benchmark_boot_std": 202.4601081600732,
        "rmse_gain_ci_lower": 649.2180310261294,
        "rmse_gain_ci_upper": 1087.5832127843087,
        "rmse_gain_boot_std": 173.56935310932775,
        "rmse_ratio_ci_lower": 0.2353156722562351,
        "rmse_ratio_ci_upper": 0.3081655844533681,
        "rmse_ratio_boot_std": 0.024919477444266477,
        "pct_reduction_ci_lower": 69.18344155466319,
        "pct_reduction_ci_upper": 76.4684327743765,
        "pct_reduction_boot_std": 2.4919477444266467,
        "rmse_gain_ci_excludes_zero": true,
        "pct_reduction_ci_excludes_zero": true,
        "varset": "parsimonious",
        "window_start": "2023-01-01",
        "window_end": "2025-12-01",
        "window": "2023:01--2025:12"
      },
      {
        "headline_model": "MS-VAR",
        "benchmark_model": "Naive",
        "n_obs": 27,
        "rmse_model": 315.24487674590387,
        "rmse_benchmark": 1350.8071814239772,
        "rmse_gain": 1035.5623046780734,
        "rmse_ratio": 0.23337518565276127,
        "pct_reduction": 76.66248143472387,
        "n_bootstrap": 10,
        "block_length": 3,
        "ci_level": 0.95,
        "bootstrap_method": "stationary_block",
        "rmse_model_ci_lower": 211.63093900280955,
        "rmse_model_ci_upper": 371.30131220246756,
        "rmse_model_boot_std": 53.49183377167129,
        "rmse_benchmark_ci_lower": 1180.1433120798472,
        "rmse_benchmark_ci_upper": 1493.0987716372113,
        "rmse_benchmark_boot_std": 106.64061900573668,
        "rmse_gain_ci_lower": 842.1047988816133,
        "rmse_gain_ci_upper": 1210.313385469657,
        "rmse_gain_boot_std": 128.47155784668482,
        "rmse_ratio_ci_lower": 0.16382357090891395,
        "rmse_ratio_ci_upper": 0.3013844802992151,
        "rmse_ratio_boot_std": 0.04967868452095351,
        "pct_reduction_ci_lower": 69.86155197007848,
        "pct_reduction_ci_upper": 83.61764290910861,
        "pct_reduction_boot_std": 4.9678684520953516,
        "rmse_gain_ci_excludes_zero": true,
        "pct_reduction_ci_excludes_zero": true,
        "varset": "bop",
        "window_start": "2023-01-01",
        "window_end": "2025-03-01",
        "window": "2023:01--2025:03"
      }
    ],
    "input_dir": "data/forecast_results_unified",
    "output_dir": "data/disentangling",
    "skip_dm": false,
    "generated_tables": [
      "table_did_rmse.tex",
      "table_a9_disentangling_uncertainty.tex",
      "table_a10_headline_rmse_uncertainty.tex"
    ]
  },
  "argv": [
    "reserves-disentangling",
    "--varsets=parsimonious,bop",
    "--models=MS-VAR,XGBoost",
    "--horizon=1",
    "--split=test",
    "--input-dir=data/forecast_results_unified",
    "--output-dir=data/disentangling",
    "--min-obs=12",
    "--bootstrap-reps=10",
    "--ci-level=0.95",
    "--random-seed=42",
    "--benchmark-model=Naive"
  ]
}